linkstart/__init__.py
linkstart/version.py
linkstart-0.1.0.dist-info/LICENSE
linkstart-0.1.0.dist-info/METADATA
linkstart-0.1.0.dist-info/WHEEL
linkstart-0.1.0.dist-info/RECORD
